{
  "tournament_id": "1812803681",
  "name": "Standard Challenge 32",
  "format": "standard",
  "date": "2025-07-18",
  "tournament_type": "challenge",
  "total_players": 32,
  "decks": [
    {
      "player": "sebastianpozzo",
      "result": "1st Place",
      "rank": 1,
      "mainboard": [
        {
          "count": 4,
          "card_name": "Agatha's Soul Cauldron"
        },
        {
          "count": 4,
          "card_name": "Fear of Missing Out"
        },
        {
          "count": 1,
          "card_name": "Glacial Dragonhunt"
        },
        {
          "count": 3,
          "card_name": "Into the Flood Maw"
        },
        {
          "count": 3,
          "card_name": "Island"
        },
        {
          "count": 1,
          "card_name": "Kiora, the Rising Tide"
        },
        {
          "count": 4,
          "card_name": "Marauding Mako"
        },
        {
          "count": 3,
          "card_name": "Mountain"
        },
        {
          "count": 4,
          "card_name": "Proft's Eidetic Memory"
        },
        {
          "count": 4,
          "card_name": "Riverpyre Verge"
        },
        {
          "count": 4,
          "card_name": "Shivan Reef"
        },
        {
          "count": 2,
          "card_name": "Soulstone Sanctuary"
        },
        {
          "count": 4,
          "card_name": "Spirebluff Canal"
        },
        {
          "count": 3,
          "card_name": "Tersa Lightshatter"
        },
        {
          "count": 2,
          "card_name": "Thundering Falls"
        },
        {
          "count": 3,
          "card_name": "Torch the Tower"
        },
        {
          "count": 4,
          "card_name": "Vivi Ornitier"
        },
        {
          "count": 3,
          "card_name": "Voldaren Thrillseeker"
        },
        {
          "count": 4,
          "card_name": "Winternight Stories"
        }
      ],
      "sideboard": [
        {
          "count": 2,
          "card_name": "Abrade"
        },
        {
          "count": 1,
          "card_name": "Broadside Barrage"
        },
        {
          "count": 2,
          "card_name": "Disdainful Stroke"
        },
        {
          "count": 2,
          "card_name": "Fire Magic"
        },
        {
          "count": 1,
          "card_name": "Lithomantic Barrage"
        },
        {
          "count": 1,
          "card_name": "Obliterating Bolt"
        },
        {
          "count": 2,
          "card_name": "Ral, Crackling Wit"
        },
        {
          "count": 2,
          "card_name": "Spell Pierce"
        },
        {
          "count": 2,
          "card_name": "Unable to Scream"
        }
      ]
    },
    {
      "player": "KadettiKersantti",
      "result": "2nd Place",
      "rank": 2,
      "mainboard": [
        {
          "count": 1,
          "card_name": "Anoint with Affliction"
        },
        {
          "count": 1,
          "card_name": "Cecil, Dark Knight"
        },
        {
          "count": 2,
          "card_name": "Cut Down"
        },
        {
          "count": 4,
          "card_name": "Darkslick Shores"
        },
        {
          "count": 4,
          "card_name": "Enduring Curiosity"
        },
        {
          "count": 3,
          "card_name": "Faebloom Trick"
        },
        {
          "count": 4,
          "card_name": "Faerie Mastermind"
        },
        {
          "count": 4,
          "card_name": "Floodpits Drowner"
        },
        {
          "count": 4,
          "card_name": "Gloomlake Verge"
        },
        {
          "count": 3,
          "card_name": "Go for the Throat"
        },
        {
          "count": 2,
          "card_name": "Into the Flood Maw"
        },
        {
          "count": 4,
          "card_name": "Island"
        },
        {
          "count": 3,
          "card_name": "Kaito, Bane of Nightmares"
        },
        {
          "count": 2,
          "card_name": "Restless Reef"
        },
        {
          "count": 3,
          "card_name": "Soulstone Sanctuary"
        },
        {
          "count": 2,
          "card_name": "Spell Stutter"
        },
        {
          "count": 4,
          "card_name": "Spyglass Siren"
        },
        {
          "count": 4,
          "card_name": "Swamp"
        },
        {
          "count": 2,
          "card_name": "Tishana's Tidebinder"
        },
        {
          "count": 4,
          "card_name": "Underground River"
        }
      ],
      "sideboard": [
        {
          "count": 2,
          "card_name": "Duress"
        },
        {
          "count": 2,
          "card_name": "Gix's Command"
        },
        {
          "count": 1,
          "card_name": "Negate"
        },
        {
          "count": 1,
          "card_name": "Neutralize the Guards"
        },
        {
          "count": 3,
          "card_name": "Preacher of the Schism"
        },
        {
          "count": 2,
          "card_name": "Sheoldred, the Apocalypse"
        },
        {
          "count": 3,
          "card_name": "Strategic Betrayal"
        },
        {
          "count": 1,
          "card_name": "Tishana's Tidebinder"
        }
      ]
    },
    {
      "player": "L1X0",
      "result": "3rd Place",
      "rank": 3,
      "mainboard": [
        {
          "count": 2,
          "card_name": "Archdruid's Charm"
        },
        {
          "count": 3,
          "card_name": "Bristly Bill, Spine Sower"
        },
        {
          "count": 4,
          "card_name": "Bushwhack"
        },
        {
          "count": 3,
          "card_name": "Escape Tunnel"
        },
        {
          "count": 4,
          "card_name": "Fabled Passage"
        },
        {
          "count": 19,
          "card_name": "Forest"
        },
        {
          "count": 4,
          "card_name": "Llanowar Elves"
        },
        {
          "count": 4,
          "card_name": "Mossborn Hydra"
        },
        {
          "count": 1,
          "card_name": "Overprotect"
        },
        {
          "count": 1,
          "card_name": "Sazh Katzroy"
        },
        {
          "count": 4,
          "card_name": "Sazh's Chocobo"
        },
        {
          "count": 1,
          "card_name": "Scavenging Ooze"
        },
        {
          "count": 4,
          "card_name": "Snakeskin Veil"
        },
        {
          "count": 2,
          "card_name": "Springbloom Druid"
        },
        {
          "count": 3,
          "card_name": "Tifa Lockhart"
        },
        {
          "count": 4,
          "card_name": "Traveling Chocobo"
        }
      ],
      "sideboard": [
        {
          "count": 1,
          "card_name": "Heritage Reclamation"
        },
        {
          "count": 2,
          "card_name": "Insidious Fungus"
        },
        {
          "count": 2,
          "card_name": "Nissa, Ascended Animist"
        },
        {
          "count": 2,
          "card_name": "Pawpatch Recruit"
        },
        {
          "count": 2,
          "card_name": "Sazh Katzroy"
        },
        {
          "count": 1,
          "card_name": "Scavenging Ooze"
        },
        {
          "count": 2,
          "card_name": "Soul-Guide Lantern"
        },
        {
          "count": 2,
          "card_name": "Tribute to the World Tree"
        },
        {
          "count": 1,
          "card_name": "Wrenn and Realmbreaker"
        }
      ]
    },
    {
      "player": "quinniac",
      "result": "4th Place",
      "rank": 4,
      "mainboard": [
        {
          "count": 1,
          "card_name": "Clockwork Percussionist"
        },
        {
          "count": 4,
          "card_name": "Copperline Gorge"
        },
        {
          "count": 4,
          "card_name": "Emberheart Challenger"
        },
        {
          "count": 1,
          "card_name": "Fiery Annihilation"
        },
        {
          "count": 1,
          "card_name": "Forest"
        },
        {
          "count": 4,
          "card_name": "Hired Claw"
        },
        {
          "count": 4,
          "card_name": "Innkeeper's Talent"
        },
        {
          "count": 4,
          "card_name": "Karplusan Forest"
        },
        {
          "count": 4,
          "card_name": "Manifold Mouse"
        },
        {
          "count": 5,
          "card_name": "Mountain"
        },
        {
          "count": 1,
          "card_name": "Obliterating Bolt"
        },
        {
          "count": 3,
          "card_name": "Overprotect"
        },
        {
          "count": 4,
          "card_name": "Pawpatch Recruit"
        },
        {
          "count": 2,
          "card_name": "Questing Druid"
        },
        {
          "count": 2,
          "card_name": "Rockface Village"
        },
        {
          "count": 4,
          "card_name": "Screaming Nemesis"
        },
        {
          "count": 2,
          "card_name": "Soulstone Sanctuary"
        },
        {
          "count": 1,
          "card_name": "Starting Town"
        },
        {
          "count": 1,
          "card_name": "Surrak, Elusive Hunter"
        },
        {
          "count": 4,
          "card_name": "Thornspire Verge"
        },
        {
          "count": 4,
          "card_name": "Torch the Tower"
        }
      ],
      "sideboard": [
        {
          "count": 1,
          "card_name": "Burst Lightning"
        },
        {
          "count": 1,
          "card_name": "Fiery Annihilation"
        },
        {
          "count": 3,
          "card_name": "Fire Magic"
        },
        {
          "count": 2,
          "card_name": "Ghost Vacuum"
        },
        {
          "count": 3,
          "card_name": "Heritage Reclamation"
        },
        {
          "count": 1,
          "card_name": "Obliterating Bolt"
        },
        {
          "count": 2,
          "card_name": "Questing Druid"
        },
        {
          "count": 2,
          "card_name": "Urabrask's Forge"
        }
      ]
    },
    {
      "player": "Univerce",
      "result": "5th Place",
      "rank": 5,
      "mainboard": [
        {
          "count": 1,
          "card_name": "Abrade"
        },
        {
          "count": 4,
          "card_name": "Agatha's Soul Cauldron"
        },
        {
          "count": 4,
          "card_name": "Fear of Missing Out"
        },
        {
          "count": 2,
          "card_name": "Fire Magic"
        },
        {
          "count": 1,
          "card_name": "Glacial Dragonhunt"
        },
        {
          "count": 3,
          "card_name": "Into the Flood Maw"
        },
        {
          "count": 3,
          "card_name": "Island"
        },
        {
          "count": 4,
          "card_name": "Marauding Mako"
        },
        {
          "count": 3,
          "card_name": "Mountain"
        },
        {
          "count": 4,
          "card_name": "Proft's Eidetic Memory"
        },
        {
          "count": 4,
          "card_name": "Riverpyre Verge"
        },
        {
          "count": 1,
          "card_name": "Scorching Dragonfire"
        },
        {
          "count": 4,
          "card_name": "Shivan Reef"
        },
        {
          "count": 2,
          "card_name": "Soulstone Sanctuary"
        },
        {
          "count": 1,
          "card_name": "Spell Pierce"
        },
        {
          "count": 4,
          "card_name": "Spirebluff Canal"
        },
        {
          "count": 1,
          "card_name": "Steamcore Scholar"
        },
        {
          "count": 2,
          "card_name": "Tersa Lightshatter"
        },
        {
          "count": 2,
          "card_name": "Thundering Falls"
        },
        {
          "count": 4,
          "card_name": "Vivi Ornitier"
        },
        {
          "count": 2,
          "card_name": "Voldaren Thrillseeker"
        },
        {
          "count": 4,
          "card_name": "Winternight Stories"
        }
      ],
      "sideboard": [
        {
          "count": 2,
          "card_name": "Abrade"
        },
        {
          "count": 2,
          "card_name": "Broadside Barrage"
        },
        {
          "count": 2,
          "card_name": "Disdainful Stroke"
        },
        {
          "count": 2,
          "card_name": "Faerie Mastermind"
        },
        {
          "count": 2,
          "card_name": "Lithomantic Barrage"
        },
        {
          "count": 1,
          "card_name": "Negate"
        },
        {
          "count": 1,
          "card_name": "Scorching Dragonfire"
        },
        {
          "count": 2,
          "card_name": "Spell Pierce"
        },
        {
          "count": 1,
          "card_name": "Torch the Tower"
        }
      ]
    },
    {
      "player": "IronBeagle",
      "result": "6th Place",
      "rank": 6,
      "mainboard": [
        {
          "count": 4,
          "card_name": "Agatha's Soul Cauldron"
        },
        {
          "count": 4,
          "card_name": "Fear of Missing Out"
        },
        {
          "count": 1,
          "card_name": "Fire Magic"
        },
        {
          "count": 1,
          "card_name": "Glacial Dragonhunt"
        },
        {
          "count": 3,
          "card_name": "Into the Flood Maw"
        },
        {
          "count": 2,
          "card_name": "Island"
        },
        {
          "count": 4,
          "card_name": "Marauding Mako"
        },
        {
          "count": 3,
          "card_name": "Mountain"
        },
        {
          "count": 4,
          "card_name": "Proft's Eidetic Memory"
        },
        {
          "count": 4,
          "card_name": "Riverpyre Verge"
        },
        {
          "count": 4,
          "card_name": "Shivan Reef"
        },
        {
          "count": 2,
          "card_name": "Soulstone Sanctuary"
        },
        {
          "count": 1,
          "card_name": "Spell Pierce"
        },
        {
          "count": 4,
          "card_name": "Spirebluff Canal"
        },
        {
          "count": 3,
          "card_name": "Tersa Lightshatter"
        },
        {
          "count": 3,
          "card_name": "Thundering Falls"
        },
        {
          "count": 2,
          "card_name": "Torch the Tower"
        },
        {
          "count": 4,
          "card_name": "Vivi Ornitier"
        },
        {
          "count": 3,
          "card_name": "Voldaren Thrillseeker"
        },
        {
          "count": 4,
          "card_name": "Winternight Stories"
        }
      ],
      "sideboard": [
        {
          "count": 1,
          "card_name": "Disdainful Stroke"
        },
        {
          "count": 2,
          "card_name": "Draconautics Engineer"
        },
        {
          "count": 2,
          "card_name": "Enduring Curiosity"
        },
        {
          "count": 3,
          "card_name": "Fire Magic"
        },
        {
          "count": 2,
          "card_name": "Negate"
        },
        {
          "count": 1,
          "card_name": "Scorching Shot"
        },
        {
          "count": 1,
          "card_name": "Spell Pierce"
        },
        {
          "count": 1,
          "card_name": "Tishana's Tidebinder"
        },
        {
          "count": 2,
          "card_name": "Unable to Scream"
        }
      ]
    },
    {
      "player": "SuperCow12653",
      "result": "7th Place",
      "rank": 7,
      "mainboard": [
        {
          "count": 4,
          "card_name": "Cut Down"
        },
        {
          "count": 4,
          "card_name": "Darkslick Shores"
        },
        {
          "count": 3,
          "card_name": "Deep-Cavern Bat"
        },
        {
          "count": 2,
          "card_name": "Duress"
        },
        {
          "count": 2,
          "card_name": "Enduring Curiosity"
        },
        {
          "count": 2,
          "card_name": "Faebloom Trick"
        },
        {
          "count": 4,
          "card_name": "Faerie Mastermind"
        },
        {
          "count": 3,
          "card_name": "Floodpits Drowner"
        },
        {
          "count": 4,
          "card_name": "Gloomlake Verge"
        },
        {
          "count": 4,
          "card_name": "Go for the Throat"
        },
        {
          "count": 3,
          "card_name": "Island"
        },
        {
          "count": 3,
          "card_name": "Kaito, Bane of Nightmares"
        },
        {
          "count": 4,
          "card_name": "Restless Reef"
        },
        {
          "count": 2,
          "card_name": "Sheoldred, the Apocalypse"
        },
        {
          "count": 2,
          "card_name": "Soulstone Sanctuary"
        },
        {
          "count": 2,
          "card_name": "Spell Stutter"
        },
        {
          "count": 4,
          "card_name": "Spyglass Siren"
        },
        {
          "count": 5,
          "card_name": "Swamp"
        },
        {
          "count": 4,
          "card_name": "Underground River"
        }
      ],
      "sideboard": [
        {
          "count": 1,
          "card_name": "Anoint with Affliction"
        },
        {
          "count": 1,
          "card_name": "Blot Out"
        },
        {
          "count": 2,
          "card_name": "Disdainful Stroke"
        },
        {
          "count": 2,
          "card_name": "Ghost Vacuum"
        },
        {
          "count": 1,
          "card_name": "Gix's Command"
        },
        {
          "count": 2,
          "card_name": "Intimidation Tactics"
        },
        {
          "count": 1,
          "card_name": "Negate"
        },
        {
          "count": 2,
          "card_name": "The Filigree Sylex"
        },
        {
          "count": 3,
          "card_name": "Tishana's Tidebinder"
        }
      ]
    },
    {
      "player": "Salvatto",
      "result": "8th Place",
      "rank": 8,
      "mainboard": [
        {
          "count": 4,
          "card_name": "Agatha's Soul Cauldron"
        },
        {
          "count": 4,
          "card_name": "Fear of Missing Out"
        },
        {
          "count": 1,
          "card_name": "Glacial Dragonhunt"
        },
        {
          "count": 3,
          "card_name": "Into the Flood Maw"
        },
        {
          "count": 3,
          "card_name": "Island"
        },
        {
          "count": 1,
          "card_name": "Kiora, the Rising Tide"
        },
        {
          "count": 4,
          "card_name": "Marauding Mako"
        },
        {
          "count": 3,
          "card_name": "Mountain"
        },
        {
          "count": 4,
          "card_name": "Proft's Eidetic Memory"
        },
        {
          "count": 4,
          "card_name": "Riverpyre Verge"
        },
        {
          "count": 4,
          "card_name": "Shivan Reef"
        },
        {
          "count": 2,
          "card_name": "Soulstone Sanctuary"
        },
        {
          "count": 4,
          "card_name": "Spirebluff Canal"
        },
        {
          "count": 3,
          "card_name": "Tersa Lightshatter"
        },
        {
          "count": 2,
          "card_name": "Thundering Falls"
        },
        {
          "count": 3,
          "card_name": "Torch the Tower"
        },
        {
          "count": 4,
          "card_name": "Vivi Ornitier"
        },
        {
          "count": 3,
          "card_name": "Voldaren Thrillseeker"
        },
        {
          "count": 4,
          "card_name": "Winternight Stories"
        }
      ],
      "sideboard": [
        {
          "count": 2,
          "card_name": "Abrade"
        },
        {
          "count": 1,
          "card_name": "Broadside Barrage"
        },
        {
          "count": 2,
          "card_name": "Disdainful Stroke"
        },
        {
          "count": 2,
          "card_name": "Fire Magic"
        },
        {
          "count": 1,
          "card_name": "Lithomantic Barrage"
        },
        {
          "count": 1,
          "card_name": "Obliterating Bolt"
        },
        {
          "count": 2,
          "card_name": "Ral, Crackling Wit"
        },
        {
          "count": 2,
          "card_name": "Spell Pierce"
        },
        {
          "count": 2,
          "card_name": "Unable to Scream"
        }
      ]
    },
    {
      "player": "Bullwinkkle6705",
      "result": "9th Place",
      "rank": 9,
      "mainboard": [
        {
          "count": 1,
          "card_name": "Agatha's Soul Cauldron"
        },
        {
          "count": 4,
          "card_name": "Astrologian's Planisphere"
        },
        {
          "count": 1,
          "card_name": "Fire Magic"
        },
        {
          "count": 1,
          "card_name": "Get Out"
        },
        {
          "count": 2,
          "card_name": "Into the Flood Maw"
        },
        {
          "count": 6,
          "card_name": "Island"
        },
        {
          "count": 3,
          "card_name": "Mountain"
        },
        {
          "count": 1,
          "card_name": "Obliterating Bolt"
        },
        {
          "count": 4,
          "card_name": "Opt"
        },
        {
          "count": 4,
          "card_name": "Riverpyre Verge"
        },
        {
          "count": 2,
          "card_name": "Roaring Furnace // Steaming Sauna"
        },
        {
          "count": 4,
          "card_name": "Shivan Reef"
        },
        {
          "count": 4,
          "card_name": "Sleight of Hand"
        },
        {
          "count": 4,
          "card_name": "Spirebluff Canal"
        },
        {
          "count": 4,
          "card_name": "Stock Up"
        },
        {
          "count": 4,
          "card_name": "Stormchaser's Talent"
        },
        {
          "count": 2,
          "card_name": "Thundertrap Trainer"
        },
        {
          "count": 4,
          "card_name": "Torch the Tower"
        },
        {
          "count": 4,
          "card_name": "Vivi Ornitier"
        },
        {
          "count": 1,
          "card_name": "Wild Ride"
        }
      ],
      "sideboard": [
        {
          "count": 2,
          "card_name": "Abrade"
        },
        {
          "count": 2,
          "card_name": "Disdainful Stroke"
        },
        {
          "count": 1,
          "card_name": "Fire Magic"
        },
        {
          "count": 2,
          "card_name": "Ghost Vacuum"
        },
        {
          "count": 1,
          "card_name": "Lithomantic Barrage"
        },
        {
          "count": 2,
          "card_name": "Ral, Crackling Wit"
        },
        {
          "count": 1,
          "card_name": "Roaring Furnace // Steaming Sauna"
        },
        {
          "count": 2,
          "card_name": "Spell Pierce"
        },
        {
          "count": 2,
          "card_name": "Unable to Scream"
        }
      ]
    },
    {
      "player": "HyPPeR",
      "result": "10th Place",
      "rank": 10,
      "mainboard": [
        {
          "count": 1,
          "card_name": "Anoint with Affliction"
        },
        {
          "count": 2,
          "card_name": "Cecil, Dark Knight"
        },
        {
          "count": 3,
          "card_name": "Cut Down"
        },
        {
          "count": 4,
          "card_name": "Darkslick Shores"
        },
        {
          "count": 4,
          "card_name": "Enduring Curiosity"
        },
        {
          "count": 3,
          "card_name": "Faebloom Trick"
        },
        {
          "count": 4,
          "card_name": "Faerie Mastermind"
        },
        {
          "count": 4,
          "card_name": "Floodpits Drowner"
        },
        {
          "count": 4,
          "card_name": "Gloomlake Verge"
        },
        {
          "count": 3,
          "card_name": "Go for the Throat"
        },
        {
          "count": 4,
          "card_name": "Island"
        },
        {
          "count": 3,
          "card_name": "Kaito, Bane of Nightmares"
        },
        {
          "count": 1,
          "card_name": "Nowhere to Run"
        },
        {
          "count": 2,
          "card_name": "Restless Reef"
        },
        {
          "count": 1,
          "card_name": "Sheoldred's Edict"
        },
        {
          "count": 3,
          "card_name": "Soulstone Sanctuary"
        },
        {
          "count": 2,
          "card_name": "Spell Stutter"
        },
        {
          "count": 4,
          "card_name": "Spyglass Siren"
        },
        {
          "count": 4,
          "card_name": "Swamp"
        },
        {
          "count": 4,
          "card_name": "Underground River"
        }
      ],
      "sideboard": [
        {
          "count": 1,
          "card_name": "Anoint with Affliction"
        },
        {
          "count": 1,
          "card_name": "Blot Out"
        },
        {
          "count": 1,
          "card_name": "Cut Down"
        },
        {
          "count": 2,
          "card_name": "Duress"
        },
        {
          "count": 2,
          "card_name": "Ghost Vacuum"
        },
        {
          "count": 2,
          "card_name": "Gix's Command"
        },
        {
          "count": 1,
          "card_name": "Negate"
        },
        {
          "count": 2,
          "card_name": "Preacher of the Schism"
        },
        {
          "count": 1,
          "card_name": "Spell Stutter"
        },
        {
          "count": 2,
          "card_name": "Tishana's Tidebinder"
        }
      ]
    },
    {
      "player": "Mottaka",
      "result": "11th Place",
      "rank": 11,
      "mainboard": [
        {
          "count": 4,
          "card_name": "Agatha's Soul Cauldron"
        },
        {
          "count": 4,
          "card_name": "Fear of Missing Out"
        },
        {
          "count": 2,
          "card_name": "Glacial Dragonhunt"
        },
        {
          "count": 3,
          "card_name": "Into the Flood Maw"
        },
        {
          "count": 2,
          "card_name": "Island"
        },
        {
          "count": 4,
          "card_name": "Marauding Mako"
        },
        {
          "count": 3,
          "card_name": "Mountain"
        },
        {
          "count": 4,
          "card_name": "Proft's Eidetic Memory"
        },
        {
          "count": 4,
          "card_name": "Riverpyre Verge"
        },
        {
          "count": 4,
          "card_name": "Shivan Reef"
        },
        {
          "count": 2,
          "card_name": "Soulstone Sanctuary"
        },
        {
          "count": 1,
          "card_name": "Spell Pierce"
        },
        {
          "count": 4,
          "card_name": "Spirebluff Canal"
        },
        {
          "count": 3,
          "card_name": "Tersa Lightshatter"
        },
        {
          "count": 3,
          "card_name": "Thundering Falls"
        },
        {
          "count": 2,
          "card_name": "Torch the Tower"
        },
        {
          "count": 4,
          "card_name": "Vivi Ornitier"
        },
        {
          "count": 3,
          "card_name": "Voldaren Thrillseeker"
        },
        {
          "count": 4,
          "card_name": "Winternight Stories"
        }
      ],
      "sideboard": [
        {
          "count": 1,
          "card_name": "Disdainful Stroke"
        },
        {
          "count": 2,
          "card_name": "Draconautics Engineer"
        },
        {
          "count": 2,
          "card_name": "Enduring Curiosity"
        },
        {
          "count": 3,
          "card_name": "Lithomantic Barrage"
        },
        {
          "count": 2,
          "card_name": "Negate"
        },
        {
          "count": 1,
          "card_name": "Scorching Shot"
        },
        {
          "count": 1,
          "card_name": "Spell Pierce"
        },
        {
          "count": 1,
          "card_name": "Tishana's Tidebinder"
        },
        {
          "count": 2,
          "card_name": "Unable to Scream"
        }
      ]
    },
    {
      "player": "SoulStrong",
      "result": "12th Place",
      "rank": 12,
      "mainboard": [
        {
          "count": 1,
          "card_name": "Anoint with Affliction"
        },
        {
          "count": 2,
          "card_name": "Cecil, Dark Knight"
        },
        {
          "count": 4,
          "card_name": "Cut Down"
        },
        {
          "count": 4,
          "card_name": "Darkslick Shores"
        },
        {
          "count": 4,
          "card_name": "Enduring Curiosity"
        },
        {
          "count": 3,
          "card_name": "Faebloom Trick"
        },
        {
          "count": 4,
          "card_name": "Faerie Mastermind"
        },
        {
          "count": 4,
          "card_name": "Floodpits Drowner"
        },
        {
          "count": 4,
          "card_name": "Gloomlake Verge"
        },
        {
          "count": 3,
          "card_name": "Go for the Throat"
        },
        {
          "count": 4,
          "card_name": "Island"
        },
        {
          "count": 3,
          "card_name": "Kaito, Bane of Nightmares"
        },
        {
          "count": 1,
          "card_name": "Lord Skitter, Sewer King"
        },
        {
          "count": 2,
          "card_name": "Restless Reef"
        },
        {
          "count": 3,
          "card_name": "Soulstone Sanctuary"
        },
        {
          "count": 2,
          "card_name": "Spell Stutter"
        },
        {
          "count": 4,
          "card_name": "Spyglass Siren"
        },
        {
          "count": 4,
          "card_name": "Swamp"
        },
        {
          "count": 4,
          "card_name": "Underground River"
        }
      ],
      "sideboard": [
        {
          "count": 1,
          "card_name": "Anoint with Affliction"
        },
        {
          "count": 1,
          "card_name": "Blot Out"
        },
        {
          "count": 2,
          "card_name": "Duress"
        },
        {
          "count": 2,
          "card_name": "Ghost Vacuum"
        },
        {
          "count": 2,
          "card_name": "Gix's Command"
        },
        {
          "count": 1,
          "card_name": "Lord Skitter, Sewer King"
        },
        {
          "count": 1,
          "card_name": "Negate"
        },
        {
          "count": 2,
          "card_name": "Preacher of the Schism"
        },
        {
          "count": 1,
          "card_name": "Spell Stutter"
        },
        {
          "count": 2,
          "card_name": "Tishana's Tidebinder"
        }
      ]
    },
    {
      "player": "cigarettesaftershrek",
      "result": "13th Place",
      "rank": 13,
      "mainboard": [
        {
          "count": 1,
          "card_name": "Abrade"
        },
        {
          "count": 4,
          "card_name": "Agatha's Soul Cauldron"
        },
        {
          "count": 4,
          "card_name": "Fear of Missing Out"
        },
        {
          "count": 1,
          "card_name": "Fire Magic"
        },
        {
          "count": 1,
          "card_name": "Glacial Dragonhunt"
        },
        {
          "count": 3,
          "card_name": "Into the Flood Maw"
        },
        {
          "count": 2,
          "card_name": "Island"
        },
        {
          "count": 4,
          "card_name": "Marauding Mako"
        },
        {
          "count": 3,
          "card_name": "Mountain"
        },
        {
          "count": 4,
          "card_name": "Proft's Eidetic Memory"
        },
        {
          "count": 4,
          "card_name": "Riverpyre Verge"
        },
        {
          "count": 4,
          "card_name": "Shivan Reef"
        },
        {
          "count": 2,
          "card_name": "Soulstone Sanctuary"
        },
        {
          "count": 4,
          "card_name": "Spirebluff Canal"
        },
        {
          "count": 3,
          "card_name": "Tersa Lightshatter"
        },
        {
          "count": 3,
          "card_name": "Thundering Falls"
        },
        {
          "count": 2,
          "card_name": "Torch the Tower"
        },
        {
          "count": 4,
          "card_name": "Vivi Ornitier"
        },
        {
          "count": 3,
          "card_name": "Voldaren Thrillseeker"
        },
        {
          "count": 4,
          "card_name": "Winternight Stories"
        }
      ],
      "sideboard": [
        {
          "count": 1,
          "card_name": "Abrade"
        },
        {
          "count": 2,
          "card_name": "Disdainful Stroke"
        },
        {
          "count": 2,
          "card_name": "Draconautics Engineer"
        },
        {
          "count": 2,
          "card_name": "Faerie Mastermind"
        },
        {
          "count": 2,
          "card_name": "Fire Magic"
        },
        {
          "count": 2,
          "card_name": "Ral, Crackling Wit"
        },
        {
          "count": 2,
          "card_name": "Spell Pierce"
        },
        {
          "count": 2,
          "card_name": "Twinmaw Stormbrood"
        }
      ]
    },
    {
      "player": "cftsoc3",
      "result": "14th Place",
      "rank": 14,
      "mainboard": [
        {
          "count": 2,
          "card_name": "Abrade"
        },
        {
          "count": 4,
          "card_name": "Analyze the Pollen"
        },
        {
          "count": 4,
          "card_name": "Botanical Sanctum"
        },
        {
          "count": 2,
          "card_name": "Bushwhack"
        },
        {
          "count": 1,
          "card_name": "Commercial District"
        },
        {
          "count": 3,
          "card_name": "Copperline Gorge"
        },
        {
          "count": 4,
          "card_name": "Enduring Vitality"
        },
        {
          "count": 2,
          "card_name": "Forest"
        },
        {
          "count": 1,
          "card_name": "Hedge Maze"
        },
        {
          "count": 1,
          "card_name": "Heritage Reclamation"
        },
        {
          "count": 2,
          "card_name": "Into the Flood Maw"
        },
        {
          "count": 2,
          "card_name": "Island"
        },
        {
          "count": 1,
          "card_name": "Karplusan Forest"
        },
        {
          "count": 1,
          "card_name": "Mountain"
        },
        {
          "count": 1,
          "card_name": "Obliterating Bolt"
        },
        {
          "count": 2,
          "card_name": "Questing Druid"
        },
        {
          "count": 2,
          "card_name": "Ral, Crackling Wit"
        },
        {
          "count": 2,
          "card_name": "Riverpyre Verge"
        },
        {
          "count": 3,
          "card_name": "Song of Totentanz"
        },
        {
          "count": 4,
          "card_name": "Stock Up"
        },
        {
          "count": 4,
          "card_name": "Stormchaser's Talent"
        },
        {
          "count": 3,
          "card_name": "Thundertrap Trainer"
        },
        {
          "count": 4,
          "card_name": "Torch the Tower"
        },
        {
          "count": 1,
          "card_name": "Twinmaw Stormbrood"
        },
        {
          "count": 2,
          "card_name": "Valley Floodcaller"
        },
        {
          "count": 2,
          "card_name": "Yavimaya Coast"
        }
      ],
      "sideboard": [
        {
          "count": 1,
          "card_name": "Abrade"
        },
        {
          "count": 1,
          "card_name": "Bounce Off"
        },
        {
          "count": 2,
          "card_name": "Faerie Mastermind"
        },
        {
          "count": 2,
          "card_name": "Fire Magic"
        },
        {
          "count": 1,
          "card_name": "Fresh Start"
        },
        {
          "count": 1,
          "card_name": "Heritage Reclamation"
        },
        {
          "count": 1,
          "card_name": "Into the Flood Maw"
        },
        {
          "count": 1,
          "card_name": "Lithomantic Barrage"
        },
        {
          "count": 2,
          "card_name": "Negate"
        },
        {
          "count": 1,
          "card_name": "Pawpatch Formation"
        },
        {
          "count": 1,
          "card_name": "Twinmaw Stormbrood"
        },
        {
          "count": 1,
          "card_name": "Valley Floodcaller"
        }
      ]
    },
    {
      "player": "boiler",
      "result": "15th Place",
      "rank": 15,
      "mainboard": [
        {
          "count": 1,
          "card_name": "Adarkar Wastes"
        },
        {
          "count": 3,
          "card_name": "Beza, the Bounding Spring"
        },
        {
          "count": 1,
          "card_name": "Change the Equation"
        },
        {
          "count": 4,
          "card_name": "Demolition Field"
        },
        {
          "count": 2,
          "card_name": "Dreams of Laguna"
        },
        {
          "count": 3,
          "card_name": "Elspeth, Storm Slayer"
        },
        {
          "count": 4,
          "card_name": "Floodfarm Verge"
        },
        {
          "count": 2,
          "card_name": "Fountainport"
        },
        {
          "count": 3,
          "card_name": "Get Lost"
        },
        {
          "count": 4,
          "card_name": "Island"
        },
        {
          "count": 3,
          "card_name": "Marang River Regent"
        },
        {
          "count": 4,
          "card_name": "Meticulous Archive"
        },
        {
          "count": 1,
          "card_name": "Negate"
        },
        {
          "count": 4,
          "card_name": "No More Lies"
        },
        {
          "count": 2,
          "card_name": "Overlord of the Mistmoors"
        },
        {
          "count": 4,
          "card_name": "Plains"
        },
        {
          "count": 2,
          "card_name": "Restless Anchorage"
        },
        {
          "count": 1,
          "card_name": "Ride's End"
        },
        {
          "count": 1,
          "card_name": "Split Up"
        },
        {
          "count": 4,
          "card_name": "Stock Up"
        },
        {
          "count": 1,
          "card_name": "Sunken Citadel"
        },
        {
          "count": 2,
          "card_name": "Temporary Lockdown"
        },
        {
          "count": 2,
          "card_name": "Three Steps Ahead"
        },
        {
          "count": 2,
          "card_name": "Ultima"
        }
      ],
      "sideboard": [
        {
          "count": 3,
          "card_name": "Clarion Conqueror"
        },
        {
          "count": 1,
          "card_name": "Devout Decree"
        },
        {
          "count": 2,
          "card_name": "Jace, the Perfected Mind"
        },
        {
          "count": 1,
          "card_name": "Overlord of the Mistmoors"
        },
        {
          "count": 3,
          "card_name": "Rest in Peace"
        },
        {
          "count": 1,
          "card_name": "Ride's End"
        },
        {
          "count": 1,
          "card_name": "Split Up"
        },
        {
          "count": 3,
          "card_name": "Tishana's Tidebinder"
        }
      ]
    },
    {
      "player": "ShadowTitan1",
      "result": "16th Place",
      "rank": 16,
      "mainboard": [
        {
          "count": 1,
          "card_name": "Abrade"
        },
        {
          "count": 4,
          "card_name": "Agatha's Soul Cauldron"
        },
        {
          "count": 1,
          "card_name": "Draconautics Engineer"
        },
        {
          "count": 4,
          "card_name": "Fear of Missing Out"
        },
        {
          "count": 1,
          "card_name": "Glacial Dragonhunt"
        },
        {
          "count": 3,
          "card_name": "Into the Flood Maw"
        },
        {
          "count": 3,
          "card_name": "Island"
        },
        {
          "count": 4,
          "card_name": "Marauding Mako"
        },
        {
          "count": 3,
          "card_name": "Mountain"
        },
        {
          "count": 4,
          "card_name": "Proft's Eidetic Memory"
        },
        {
          "count": 4,
          "card_name": "Riverpyre Verge"
        },
        {
          "count": 4,
          "card_name": "Shivan Reef"
        },
        {
          "count": 2,
          "card_name": "Soulstone Sanctuary"
        },
        {
          "count": 1,
          "card_name": "Spell Pierce"
        },
        {
          "count": 4,
          "card_name": "Spirebluff Canal"
        },
        {
          "count": 3,
          "card_name": "Tersa Lightshatter"
        },
        {
          "count": 2,
          "card_name": "Thundering Falls"
        },
        {
          "count": 2,
          "card_name": "Torch the Tower"
        },
        {
          "count": 4,
          "card_name": "Vivi Ornitier"
        },
        {
          "count": 2,
          "card_name": "Voldaren Thrillseeker"
        },
        {
          "count": 4,
          "card_name": "Winternight Stories"
        }
      ],
      "sideboard": [
        {
          "count": 1,
          "card_name": "Disdainful Stroke"
        },
        {
          "count": 1,
          "card_name": "Draconautics Engineer"
        },
        {
          "count": 2,
          "card_name": "Enduring Curiosity"
        },
        {
          "count": 1,
          "card_name": "Faerie Mastermind"
        },
        {
          "count": 2,
          "card_name": "Fire Magic"
        },
        {
          "count": 2,
          "card_name": "Lithomantic Barrage"
        },
        {
          "count": 1,
          "card_name": "Negate"
        },
        {
          "count": 1,
          "card_name": "Spell Pierce"
        },
        {
          "count": 2,
          "card_name": "Twinmaw Stormbrood"
        },
        {
          "count": 2,
          "card_name": "Unable to Scream"
        }
      ]
    },
    {
      "player": "deleon91",
      "result": "17th Place",
      "rank": 17,
      "mainboard": [
        {
          "count": 4,
          "card_name": "Burst Lightning"
        },
        {
          "count": 4,
          "card_name": "Copperline Gorge"
        },
        {
          "count": 4,
          "card_name": "Emberheart Challenger"
        },
        {
          "count": 1,
          "card_name": "Forest"
        },
        {
          "count": 4,
          "card_name": "Hired Claw"
        },
        {
          "count": 3,
          "card_name": "Innkeeper's Talent"
        },
        {
          "count": 4,
          "card_name": "Karplusan Forest"
        },
        {
          "count": 4,
          "card_name": "Manifold Mouse"
        },
        {
          "count": 2,
          "card_name": "Monastery Swiftspear"
        },
        {
          "count": 5,
          "card_name": "Mountain"
        },
        {
          "count": 3,
          "card_name": "Overprotect"
        },
        {
          "count": 4,
          "card_name": "Pawpatch Recruit"
        },
        {
          "count": 2,
          "card_name": "Rockface Village"
        },
        {
          "count": 4,
          "card_name": "Screaming Nemesis"
        },
        {
          "count": 2,
          "card_name": "Soulstone Sanctuary"
        },
        {
          "count": 4,
          "card_name": "Thornspire Verge"
        },
        {
          "count": 2,
          "card_name": "Twinmaw Stormbrood"
        },
        {
          "count": 4,
          "card_name": "Witchstalker Frenzy"
        }
      ],
      "sideboard": [
        {
          "count": 4,
          "card_name": "Heritage Reclamation"
        },
        {
          "count": 3,
          "card_name": "Obliterating Bolt"
        },
        {
          "count": 2,
          "card_name": "Pyroclasm"
        },
        {
          "count": 2,
          "card_name": "Scorching Dragonfire"
        },
        {
          "count": 4,
          "card_name": "Urabrask's Forge"
        }
      ]
    },
    {
      "player": "AJV20",
      "result": "18th Place",
      "rank": 18,
      "mainboard": [
        {
          "count": 2,
          "card_name": "Abrade"
        },
        {
          "count": 4,
          "card_name": "Agatha's Soul Cauldron"
        },
        {
          "count": 4,
          "card_name": "Fear of Missing Out"
        },
        {
          "count": 2,
          "card_name": "Glacial Dragonhunt"
        },
        {
          "count": 3,
          "card_name": "Into the Flood Maw"
        },
        {
          "count": 2,
          "card_name": "Island"
        },
        {
          "count": 4,
          "card_name": "Marauding Mako"
        },
        {
          "count": 3,
          "card_name": "Mountain"
        },
        {
          "count": 4,
          "card_name": "Proft's Eidetic Memory"
        },
        {
          "count": 4,
          "card_name": "Riverpyre Verge"
        },
        {
          "count": 4,
          "card_name": "Shivan Reef"
        },
        {
          "count": 2,
          "card_name": "Soulstone Sanctuary"
        },
        {
          "count": 1,
          "card_name": "Spell Pierce"
        },
        {
          "count": 4,
          "card_name": "Spirebluff Canal"
        },
        {
          "count": 3,
          "card_name": "Tersa Lightshatter"
        },
        {
          "count": 3,
          "card_name": "Thundering Falls"
        },
        {
          "count": 4,
          "card_name": "Vivi Ornitier"
        },
        {
          "count": 3,
          "card_name": "Voldaren Thrillseeker"
        },
        {
          "count": 4,
          "card_name": "Winternight Stories"
        }
      ],
      "sideboard": [
        {
          "count": 1,
          "card_name": "Abrade"
        },
        {
          "count": 2,
          "card_name": "Draconautics Engineer"
        },
        {
          "count": 2,
          "card_name": "Enduring Curiosity"
        },
        {
          "count": 3,
          "card_name": "Lithomantic Barrage"
        },
        {
          "count": 2,
          "card_name": "Negate"
        },
        {
          "count": 1,
          "card_name": "Scorching Shot"
        },
        {
          "count": 1,
          "card_name": "Spell Pierce"
        },
        {
          "count": 3,
          "card_name": "Unable to Scream"
        }
      ]
    },
    {
      "player": "aarrgh",
      "result": "19th Place",
      "rank": 19,
      "mainboard": [
        {
          "count": 4,
          "card_name": "Beseech the Mirror"
        },
        {
          "count": 4,
          "card_name": "Blazemire Verge"
        },
        {
          "count": 4,
          "card_name": "Bleachbone Verge"
        },
        {
          "count": 3,
          "card_name": "Caves of Koilos"
        },
        {
          "count": 3,
          "card_name": "Concealed Courtyard"
        },
        {
          "count": 1,
          "card_name": "Day of Judgment"
        },
        {
          "count": 4,
          "card_name": "Demonic Pact"
        },
        {
          "count": 2,
          "card_name": "Grim Bauble"
        },
        {
          "count": 1,
          "card_name": "Harmless Offering"
        },
        {
          "count": 2,
          "card_name": "Loran of the Third Path"
        },
        {
          "count": 3,
          "card_name": "Momentum Breaker"
        },
        {
          "count": 3,
          "card_name": "Nowhere to Run"
        },
        {
          "count": 4,
          "card_name": "Nurturing Pixie"
        },
        {
          "count": 2,
          "card_name": "Plains"
        },
        {
          "count": 4,
          "card_name": "Shadowy Backstreet"
        },
        {
          "count": 4,
          "card_name": "Sunpearl Kirin"
        },
        {
          "count": 4,
          "card_name": "Swamp"
        },
        {
          "count": 3,
          "card_name": "Temporary Lockdown"
        },
        {
          "count": 1,
          "card_name": "The End"
        },
        {
          "count": 4,
          "card_name": "Tinybones Joins Up"
        }
      ],
      "sideboard": [
        {
          "count": 1,
          "card_name": "Beza, the Bounding Spring"
        },
        {
          "count": 3,
          "card_name": "Dark Confidant"
        },
        {
          "count": 2,
          "card_name": "Dreams of Steel and Oil"
        },
        {
          "count": 2,
          "card_name": "Duress"
        },
        {
          "count": 2,
          "card_name": "Exorcise"
        },
        {
          "count": 2,
          "card_name": "Rest in Peace"
        },
        {
          "count": 1,
          "card_name": "Sheoldred's Edict"
        },
        {
          "count": 1,
          "card_name": "Sheoldred, the Apocalypse"
        },
        {
          "count": 1,
          "card_name": "Unholy Annex // Ritual Chamber"
        }
      ]
    },
    {
      "player": "VitorCarvalho01",
      "result": "20th Place",
      "rank": 20,
      "mainboard": [
        {
          "count": 1,
          "card_name": "Anoint with Affliction"
        },
        {
          "count": 3,
          "card_name": "Cut Down"
        },
        {
          "count": 4,
          "card_name": "Darkslick Shores"
        },
        {
          "count": 4,
          "card_name": "Deep-Cavern Bat"
        },
        {
          "count": 4,
          "card_name": "Enduring Curiosity"
        },
        {
          "count": 1,
          "card_name": "Faebloom Trick"
        },
        {
          "count": 2,
          "card_name": "Faerie Mastermind"
        },
        {
          "count": 4,
          "card_name": "Floodpits Drowner"
        },
        {
          "count": 4,
          "card_name": "Gloomlake Verge"
        },
        {
          "count": 3,
          "card_name": "Go for the Throat"
        },
        {
          "count": 5,
          "card_name": "Island"
        },
        {
          "count": 3,
          "card_name": "Kaito, Bane of Nightmares"
        },
        {
          "count": 2,
          "card_name": "Phantom Interference"
        },
        {
          "count": 2,
          "card_name": "Restless Reef"
        },
        {
          "count": 1,
          "card_name": "Sheoldred's Edict"
        },
        {
          "count": 1,
          "card_name": "Sheoldred, the Apocalypse"
        },
        {
          "count": 2,
          "card_name": "Soulstone Sanctuary"
        },
        {
          "count": 4,
          "card_name": "Spyglass Siren"
        },
        {
          "count": 4,
          "card_name": "Swamp"
        },
        {
          "count": 2,
          "card_name": "Tishana's Tidebinder"
        },
        {
          "count": 4,
          "card_name": "Underground River"
        }
      ],
      "sideboard": [
        {
          "count": 1,
          "card_name": "Anoint with Affliction"
        },
        {
          "count": 1,
          "card_name": "Cut Down"
        },
        {
          "count": 1,
          "card_name": "Disdainful Stroke"
        },
        {
          "count": 2,
          "card_name": "Duress"
        },
        {
          "count": 1,
          "card_name": "Faebloom Trick"
        },
        {
          "count": 1,
          "card_name": "Faerie Mastermind"
        },
        {
          "count": 1,
          "card_name": "Ghost Vacuum"
        },
        {
          "count": 2,
          "card_name": "Gix's Command"
        },
        {
          "count": 1,
          "card_name": "Intimidation Tactics"
        },
        {
          "count": 1,
          "card_name": "Kaito, Bane of Nightmares"
        },
        {
          "count": 1,
          "card_name": "Negate"
        },
        {
          "count": 1,
          "card_name": "Preacher of the Schism"
        },
        {
          "count": 1,
          "card_name": "Tishana's Tidebinder"
        }
      ]
    },
    {
      "player": "EdgarB",
      "result": "21th Place",
      "rank": 21,
      "mainboard": [
        {
          "count": 1,
          "card_name": "Abrade"
        },
        {
          "count": 1,
          "card_name": "Agatha's Soul Cauldron"
        },
        {
          "count": 4,
          "card_name": "Astrologian's Planisphere"
        },
        {
          "count": 1,
          "card_name": "Fire Magic"
        },
        {
          "count": 1,
          "card_name": "Get Out"
        },
        {
          "count": 2,
          "card_name": "Into the Flood Maw"
        },
        {
          "count": 6,
          "card_name": "Island"
        },
        {
          "count": 2,
          "card_name": "Mountain"
        },
        {
          "count": 4,
          "card_name": "Opt"
        },
        {
          "count": 2,
          "card_name": "Ral, Crackling Wit"
        },
        {
          "count": 1,
          "card_name": "Rebel Salvo"
        },
        {
          "count": 4,
          "card_name": "Riverpyre Verge"
        },
        {
          "count": 1,
          "card_name": "Roaring Furnace // Steaming Sauna"
        },
        {
          "count": 4,
          "card_name": "Shivan Reef"
        },
        {
          "count": 4,
          "card_name": "Sleight of Hand"
        },
        {
          "count": 4,
          "card_name": "Spirebluff Canal"
        },
        {
          "count": 4,
          "card_name": "Stock Up"
        },
        {
          "count": 4,
          "card_name": "Stormchaser's Talent"
        },
        {
          "count": 1,
          "card_name": "Thundering Falls"
        },
        {
          "count": 1,
          "card_name": "Thundertrap Trainer"
        },
        {
          "count": 4,
          "card_name": "Torch the Tower"
        },
        {
          "count": 4,
          "card_name": "Vivi Ornitier"
        }
      ],
      "sideboard": [
        {
          "count": 1,
          "card_name": "Abrade"
        },
        {
          "count": 1,
          "card_name": "Agatha's Soul Cauldron"
        },
        {
          "count": 1,
          "card_name": "Brotherhood's End"
        },
        {
          "count": 2,
          "card_name": "Change the Equation"
        },
        {
          "count": 1,
          "card_name": "Disdainful Stroke"
        },
        {
          "count": 3,
          "card_name": "Faerie Mastermind"
        },
        {
          "count": 2,
          "card_name": "Fire Magic"
        },
        {
          "count": 1,
          "card_name": "Lithomantic Barrage"
        },
        {
          "count": 1,
          "card_name": "Negate"
        },
        {
          "count": 1,
          "card_name": "Rebel Salvo"
        },
        {
          "count": 1,
          "card_name": "Spell Pierce"
        }
      ]
    },
    {
      "player": "GzusReturned",
      "result": "22th Place",
      "rank": 22,
      "mainboard": [
        {
          "count": 1,
          "card_name": "Anoint with Affliction"
        },
        {
          "count": 3,
          "card_name": "Cut Down"
        },
        {
          "count": 4,
          "card_name": "Darkslick Shores"
        },
        {
          "count": 4,
          "card_name": "Deep-Cavern Bat"
        },
        {
          "count": 4,
          "card_name": "Enduring Curiosity"
        },
        {
          "count": 1,
          "card_name": "Faebloom Trick"
        },
        {
          "count": 2,
          "card_name": "Faerie Mastermind"
        },
        {
          "count": 4,
          "card_name": "Floodpits Drowner"
        },
        {
          "count": 4,
          "card_name": "Gloomlake Verge"
        },
        {
          "count": 3,
          "card_name": "Go for the Throat"
        },
        {
          "count": 5,
          "card_name": "Island"
        },
        {
          "count": 3,
          "card_name": "Kaito, Bane of Nightmares"
        },
        {
          "count": 2,
          "card_name": "Phantom Interference"
        },
        {
          "count": 2,
          "card_name": "Restless Reef"
        },
        {
          "count": 1,
          "card_name": "Sheoldred's Edict"
        },
        {
          "count": 1,
          "card_name": "Sheoldred, the Apocalypse"
        },
        {
          "count": 2,
          "card_name": "Soulstone Sanctuary"
        },
        {
          "count": 4,
          "card_name": "Spyglass Siren"
        },
        {
          "count": 4,
          "card_name": "Swamp"
        },
        {
          "count": 2,
          "card_name": "Tishana's Tidebinder"
        },
        {
          "count": 4,
          "card_name": "Underground River"
        }
      ],
      "sideboard": [
        {
          "count": 1,
          "card_name": "Anoint with Affliction"
        },
        {
          "count": 1,
          "card_name": "Cut Down"
        },
        {
          "count": 1,
          "card_name": "Disdainful Stroke"
        },
        {
          "count": 2,
          "card_name": "Duress"
        },
        {
          "count": 1,
          "card_name": "Faebloom Trick"
        },
        {
          "count": 1,
          "card_name": "Faerie Mastermind"
        },
        {
          "count": 1,
          "card_name": "Ghost Vacuum"
        },
        {
          "count": 2,
          "card_name": "Gix's Command"
        },
        {
          "count": 1,
          "card_name": "Intimidation Tactics"
        },
        {
          "count": 1,
          "card_name": "Kaito, Bane of Nightmares"
        },
        {
          "count": 1,
          "card_name": "Negate"
        },
        {
          "count": 1,
          "card_name": "Preacher of the Schism"
        },
        {
          "count": 1,
          "card_name": "Tishana's Tidebinder"
        }
      ]
    },
    {
      "player": "Comrade1312",
      "result": "23th Place",
      "rank": 23,
      "mainboard": [
        {
          "count": 4,
          "card_name": "Analyze the Pollen"
        },
        {
          "count": 4,
          "card_name": "Botanical Sanctum"
        },
        {
          "count": 2,
          "card_name": "Copperline Gorge"
        },
        {
          "count": 4,
          "card_name": "Enduring Vitality"
        },
        {
          "count": 2,
          "card_name": "Forest"
        },
        {
          "count": 1,
          "card_name": "Into the Flood Maw"
        },
        {
          "count": 2,
          "card_name": "Island"
        },
        {
          "count": 2,
          "card_name": "Karplusan Forest"
        },
        {
          "count": 1,
          "card_name": "Mountain"
        },
        {
          "count": 2,
          "card_name": "Obliterating Bolt"
        },
        {
          "count": 4,
          "card_name": "Opt"
        },
        {
          "count": 4,
          "card_name": "Questing Druid"
        },
        {
          "count": 4,
          "card_name": "Sleight of Hand"
        },
        {
          "count": 3,
          "card_name": "Spirebluff Canal"
        },
        {
          "count": 4,
          "card_name": "Stock Up"
        },
        {
          "count": 4,
          "card_name": "Stormchaser's Talent"
        },
        {
          "count": 3,
          "card_name": "Stormsplitter"
        },
        {
          "count": 3,
          "card_name": "Third Path Iconoclast"
        },
        {
          "count": 4,
          "card_name": "Torch the Tower"
        },
        {
          "count": 1,
          "card_name": "Willowrush Verge"
        },
        {
          "count": 2,
          "card_name": "Yavimaya Coast"
        }
      ],
      "sideboard": [
        {
          "count": 2,
          "card_name": "Fire Magic"
        },
        {
          "count": 1,
          "card_name": "Get Out"
        },
        {
          "count": 1,
          "card_name": "Ghost Vacuum"
        },
        {
          "count": 1,
          "card_name": "Heritage Reclamation"
        },
        {
          "count": 2,
          "card_name": "Into the Flood Maw"
        },
        {
          "count": 2,
          "card_name": "Negate"
        },
        {
          "count": 1,
          "card_name": "Obliterating Bolt"
        },
        {
          "count": 2,
          "card_name": "Ral, Crackling Wit"
        },
        {
          "count": 2,
          "card_name": "Tishana's Tidebinder"
        },
        {
          "count": 1,
          "card_name": "Twinmaw Stormbrood"
        }
      ]
    },
    {
      "player": "OafMcNamara",
      "result": "24th Place",
      "rank": 24,
      "mainboard": [
        {
          "count": 1,
          "card_name": "Abrade"
        },
        {
          "count": 4,
          "card_name": "Agatha's Soul Cauldron"
        },
        {
          "count": 4,
          "card_name": "Fear of Missing Out"
        },
        {
          "count": 1,
          "card_name": "Glacial Dragonhunt"
        },
        {
          "count": 3,
          "card_name": "Into the Flood Maw"
        },
        {
          "count": 3,
          "card_name": "Island"
        },
        {
          "count": 4,
          "card_name": "Marauding Mako"
        },
        {
          "count": 3,
          "card_name": "Mountain"
        },
        {
          "count": 4,
          "card_name": "Proft's Eidetic Memory"
        },
        {
          "count": 4,
          "card_name": "Riverpyre Verge"
        },
        {
          "count": 4,
          "card_name": "Shivan Reef"
        },
        {
          "count": 1,
          "card_name": "Shore Up"
        },
        {
          "count": 2,
          "card_name": "Soulstone Sanctuary"
        },
        {
          "count": 4,
          "card_name": "Spirebluff Canal"
        },
        {
          "count": 2,
          "card_name": "Tersa Lightshatter"
        },
        {
          "count": 2,
          "card_name": "Thundering Falls"
        },
        {
          "count": 3,
          "card_name": "Torch the Tower"
        },
        {
          "count": 4,
          "card_name": "Vivi Ornitier"
        },
        {
          "count": 2,
          "card_name": "Voldaren Thrillseeker"
        },
        {
          "count": 1,
          "card_name": "Wild Ride"
        },
        {
          "count": 4,
          "card_name": "Winternight Stories"
        }
      ],
      "sideboard": [
        {
          "count": 2,
          "card_name": "Abrade"
        },
        {
          "count": 2,
          "card_name": "Disdainful Stroke"
        },
        {
          "count": 2,
          "card_name": "Faerie Mastermind"
        },
        {
          "count": 2,
          "card_name": "Fire Magic"
        },
        {
          "count": 2,
          "card_name": "Lithomantic Barrage"
        },
        {
          "count": 1,
          "card_name": "Negate"
        },
        {
          "count": 2,
          "card_name": "Twinmaw Stormbrood"
        },
        {
          "count": 2,
          "card_name": "Unable to Scream"
        }
      ]
    },
    {
      "player": "WadeB",
      "result": "25th Place",
      "rank": 25,
      "mainboard": [
        {
          "count": 2,
          "card_name": "Analyze the Pollen"
        },
        {
          "count": 2,
          "card_name": "Cavern of Souls"
        },
        {
          "count": 2,
          "card_name": "Dredger's Insight"
        },
        {
          "count": 4,
          "card_name": "Esper Origins"
        },
        {
          "count": 1,
          "card_name": "Floodfarm Verge"
        },
        {
          "count": 2,
          "card_name": "Forest"
        },
        {
          "count": 2,
          "card_name": "Get Lost"
        },
        {
          "count": 1,
          "card_name": "Hedge Maze"
        },
        {
          "count": 4,
          "card_name": "Hushwood Verge"
        },
        {
          "count": 1,
          "card_name": "Island"
        },
        {
          "count": 3,
          "card_name": "Leyline Binding"
        },
        {
          "count": 4,
          "card_name": "Lush Portico"
        },
        {
          "count": 2,
          "card_name": "Overlord of the Balemurk"
        },
        {
          "count": 4,
          "card_name": "Overlord of the Hauntwoods"
        },
        {
          "count": 4,
          "card_name": "Overlord of the Mistmoors"
        },
        {
          "count": 2,
          "card_name": "Plains"
        },
        {
          "count": 2,
          "card_name": "Shadowy Backstreet"
        },
        {
          "count": 3,
          "card_name": "Summon: Fenrir"
        },
        {
          "count": 1,
          "card_name": "Swamp"
        },
        {
          "count": 2,
          "card_name": "Temporary Lockdown"
        },
        {
          "count": 2,
          "card_name": "Underground Mortuary"
        },
        {
          "count": 3,
          "card_name": "Wastewood Verge"
        },
        {
          "count": 4,
          "card_name": "Yuna, Hope of Spira"
        },
        {
          "count": 4,
          "card_name": "Zur, Eternal Schemer"
        }
      ],
      "sideboard": [
        {
          "count": 1,
          "card_name": "Beza, the Bounding Spring"
        },
        {
          "count": 1,
          "card_name": "Day of Judgment"
        },
        {
          "count": 2,
          "card_name": "Duress"
        },
        {
          "count": 1,
          "card_name": "Elesh Norn, Mother of Machines"
        },
        {
          "count": 1,
          "card_name": "Get Lost"
        },
        {
          "count": 2,
          "card_name": "Ghost Vacuum"
        },
        {
          "count": 2,
          "card_name": "Go for the Throat"
        },
        {
          "count": 1,
          "card_name": "Tear Asunder"
        },
        {
          "count": 2,
          "card_name": "Temporary Lockdown"
        },
        {
          "count": 1,
          "card_name": "The Swarmweaver"
        },
        {
          "count": 1,
          "card_name": "Tranquil Frillback"
        }
      ]
    },
    {
      "player": "kcomedina",
      "result": "26th Place",
      "rank": 26,
      "mainboard": [
        {
          "count": 1,
          "card_name": "Anoint with Affliction"
        },
        {
          "count": 2,
          "card_name": "Cecil, Dark Knight"
        },
        {
          "count": 3,
          "card_name": "Cut Down"
        },
        {
          "count": 4,
          "card_name": "Darkslick Shores"
        },
        {
          "count": 4,
          "card_name": "Enduring Curiosity"
        },
        {
          "count": 4,
          "card_name": "Faebloom Trick"
        },
        {
          "count": 4,
          "card_name": "Faerie Mastermind"
        },
        {
          "count": 4,
          "card_name": "Floodpits Drowner"
        },
        {
          "count": 4,
          "card_name": "Gloomlake Verge"
        },
        {
          "count": 3,
          "card_name": "Go for the Throat"
        },
        {
          "count": 4,
          "card_name": "Island"
        },
        {
          "count": 3,
          "card_name": "Kaito, Bane of Nightmares"
        },
        {
          "count": 1,
          "card_name": "Nowhere to Run"
        },
        {
          "count": 2,
          "card_name": "Restless Reef"
        },
        {
          "count": 3,
          "card_name": "Soulstone Sanctuary"
        },
        {
          "count": 2,
          "card_name": "Spell Stutter"
        },
        {
          "count": 4,
          "card_name": "Spyglass Siren"
        },
        {
          "count": 4,
          "card_name": "Swamp"
        },
        {
          "count": 4,
          "card_name": "Underground River"
        }
      ],
      "sideboard": [
        {
          "count": 1,
          "card_name": "Anoint with Affliction"
        },
        {
          "count": 1,
          "card_name": "Blot Out"
        },
        {
          "count": 1,
          "card_name": "Cut Down"
        },
        {
          "count": 2,
          "card_name": "Duress"
        },
        {
          "count": 2,
          "card_name": "Ghost Vacuum"
        },
        {
          "count": 2,
          "card_name": "Gix's Command"
        },
        {
          "count": 1,
          "card_name": "Negate"
        },
        {
          "count": 2,
          "card_name": "Preacher of the Schism"
        },
        {
          "count": 1,
          "card_name": "Spell Stutter"
        },
        {
          "count": 2,
          "card_name": "Tishana's Tidebinder"
        }
      ]
    },
    {
      "player": "Varo",
      "result": "27th Place",
      "rank": 27,
      "mainboard": [
        {
          "count": 1,
          "card_name": "Abrade"
        },
        {
          "count": 1,
          "card_name": "Agatha's Soul Cauldron"
        },
        {
          "count": 4,
          "card_name": "Astrologian's Planisphere"
        },
        {
          "count": 2,
          "card_name": "Get Out"
        },
        {
          "count": 2,
          "card_name": "Into the Flood Maw"
        },
        {
          "count": 7,
          "card_name": "Island"
        },
        {
          "count": 3,
          "card_name": "Mountain"
        },
        {
          "count": 1,
          "card_name": "Obliterating Bolt"
        },
        {
          "count": 4,
          "card_name": "Opt"
        },
        {
          "count": 1,
          "card_name": "Ral, Crackling Wit"
        },
        {
          "count": 1,
          "card_name": "Rebel Salvo"
        },
        {
          "count": 4,
          "card_name": "Riverpyre Verge"
        },
        {
          "count": 1,
          "card_name": "Roaring Furnace // Steaming Sauna"
        },
        {
          "count": 4,
          "card_name": "Shivan Reef"
        },
        {
          "count": 4,
          "card_name": "Sleight of Hand"
        },
        {
          "count": 4,
          "card_name": "Spirebluff Canal"
        },
        {
          "count": 4,
          "card_name": "Stock Up"
        },
        {
          "count": 4,
          "card_name": "Stormchaser's Talent"
        },
        {
          "count": 4,
          "card_name": "Torch the Tower"
        },
        {
          "count": 4,
          "card_name": "Vivi Ornitier"
        }
      ],
      "sideboard": [
        {
          "count": 1,
          "card_name": "Abrade"
        },
        {
          "count": 1,
          "card_name": "Agatha's Soul Cauldron"
        },
        {
          "count": 2,
          "card_name": "Disdainful Stroke"
        },
        {
          "count": 2,
          "card_name": "Enduring Curiosity"
        },
        {
          "count": 2,
          "card_name": "Faerie Mastermind"
        },
        {
          "count": 2,
          "card_name": "Fire Magic"
        },
        {
          "count": 1,
          "card_name": "Into the Flood Maw"
        },
        {
          "count": 2,
          "card_name": "Lithomantic Barrage"
        },
        {
          "count": 1,
          "card_name": "Ral, Crackling Wit"
        },
        {
          "count": 1,
          "card_name": "Rebel Salvo"
        }
      ]
    },
    {
      "player": "matttothec",
      "result": "28th Place",
      "rank": 28,
      "mainboard": [
        {
          "count": 1,
          "card_name": "Bitter Triumph"
        },
        {
          "count": 3,
          "card_name": "Caustic Exhale"
        },
        {
          "count": 1,
          "card_name": "Cavern of Souls"
        },
        {
          "count": 4,
          "card_name": "Darkslick Shores"
        },
        {
          "count": 2,
          "card_name": "Deadly Cover-Up"
        },
        {
          "count": 2,
          "card_name": "Dispelling Exhale"
        },
        {
          "count": 2,
          "card_name": "Doomsday Excruciator"
        },
        {
          "count": 1,
          "card_name": "Feed the Cycle"
        },
        {
          "count": 4,
          "card_name": "Gloomlake Verge"
        },
        {
          "count": 2,
          "card_name": "Go for the Throat"
        },
        {
          "count": 3,
          "card_name": "Jace, the Perfected Mind"
        },
        {
          "count": 2,
          "card_name": "Marang River Regent"
        },
        {
          "count": 4,
          "card_name": "Oildeep Gearhulk"
        },
        {
          "count": 1,
          "card_name": "Phantom Interference"
        },
        {
          "count": 4,
          "card_name": "Restless Reef"
        },
        {
          "count": 2,
          "card_name": "Scavenger Regent"
        },
        {
          "count": 2,
          "card_name": "Shoot the Sheriff"
        },
        {
          "count": 4,
          "card_name": "Stock Up"
        },
        {
          "count": 5,
          "card_name": "Swamp"
        },
        {
          "count": 2,
          "card_name": "Three Steps Ahead"
        },
        {
          "count": 2,
          "card_name": "Tishana's Tidebinder"
        },
        {
          "count": 4,
          "card_name": "Undercity Sewers"
        },
        {
          "count": 3,
          "card_name": "Underground River"
        }
      ],
      "sideboard": [
        {
          "count": 2,
          "card_name": "Blot Out"
        },
        {
          "count": 1,
          "card_name": "Deadly Cover-Up"
        },
        {
          "count": 2,
          "card_name": "Duress"
        },
        {
          "count": 2,
          "card_name": "Faerie Mastermind"
        },
        {
          "count": 2,
          "card_name": "Ghost Vacuum"
        },
        {
          "count": 2,
          "card_name": "Negate"
        },
        {
          "count": 2,
          "card_name": "Sheoldred, the Apocalypse"
        },
        {
          "count": 2,
          "card_name": "Tishana's Tidebinder"
        }
      ]
    },
    {
      "player": "supersam710",
      "result": "29th Place",
      "rank": 29,
      "mainboard": [
        {
          "count": 1,
          "card_name": "Abrade"
        },
        {
          "count": 1,
          "card_name": "Agatha's Soul Cauldron"
        },
        {
          "count": 1,
          "card_name": "Astrologian's Planisphere"
        },
        {
          "count": 1,
          "card_name": "Fires of Victory"
        },
        {
          "count": 2,
          "card_name": "Get Out"
        },
        {
          "count": 1,
          "card_name": "Into the Flood Maw"
        },
        {
          "count": 7,
          "card_name": "Island"
        },
        {
          "count": 2,
          "card_name": "Jace Reawakened"
        },
        {
          "count": 1,
          "card_name": "Mountain"
        },
        {
          "count": 1,
          "card_name": "Obliterating Bolt"
        },
        {
          "count": 4,
          "card_name": "Opt"
        },
        {
          "count": 4,
          "card_name": "Riverpyre Verge"
        },
        {
          "count": 4,
          "card_name": "Shivan Reef"
        },
        {
          "count": 4,
          "card_name": "Sleight of Hand"
        },
        {
          "count": 2,
          "card_name": "Spell Pierce"
        },
        {
          "count": 4,
          "card_name": "Spirebluff Canal"
        },
        {
          "count": 4,
          "card_name": "Stock Up"
        },
        {
          "count": 4,
          "card_name": "Stormchaser's Talent"
        },
        {
          "count": 1,
          "card_name": "Thundering Falls"
        },
        {
          "count": 3,
          "card_name": "Thundertrap Trainer"
        },
        {
          "count": 4,
          "card_name": "Torch the Tower"
        },
        {
          "count": 4,
          "card_name": "Vivi Ornitier"
        }
      ],
      "sideboard": [
        {
          "count": 1,
          "card_name": "Abhorrent Oculus"
        },
        {
          "count": 1,
          "card_name": "Agatha's Soul Cauldron"
        },
        {
          "count": 2,
          "card_name": "Change the Equation"
        },
        {
          "count": 2,
          "card_name": "Disdainful Stroke"
        },
        {
          "count": 3,
          "card_name": "Fire Magic"
        },
        {
          "count": 1,
          "card_name": "Into the Flood Maw"
        },
        {
          "count": 2,
          "card_name": "Lithomantic Barrage"
        },
        {
          "count": 2,
          "card_name": "Ral, Crackling Wit"
        },
        {
          "count": 1,
          "card_name": "Sorcerous Spyglass"
        }
      ]
    },
    {
      "player": "_Davimorais",
      "result": "30th Place",
      "rank": 30,
      "mainboard": [
        {
          "count": 1,
          "card_name": "Analyze the Pollen"
        },
        {
          "count": 2,
          "card_name": "Cavern of Souls"
        },
        {
          "count": 2,
          "card_name": "Dredger's Insight"
        },
        {
          "count": 2,
          "card_name": "Esper Origins"
        },
        {
          "count": 1,
          "card_name": "Floodfarm Verge"
        },
        {
          "count": 2,
          "card_name": "Forest"
        },
        {
          "count": 2,
          "card_name": "Get Lost"
        },
        {
          "count": 3,
          "card_name": "Go for the Throat"
        },
        {
          "count": 4,
          "card_name": "Hushwood Verge"
        },
        {
          "count": 1,
          "card_name": "Island"
        },
        {
          "count": 4,
          "card_name": "Lush Portico"
        },
        {
          "count": 2,
          "card_name": "Overlord of the Balemurk"
        },
        {
          "count": 3,
          "card_name": "Overlord of the Hauntwoods"
        },
        {
          "count": 3,
          "card_name": "Overlord of the Mistmoors"
        },
        {
          "count": 2,
          "card_name": "Plains"
        },
        {
          "count": 2,
          "card_name": "Shadowy Backstreet"
        },
        {
          "count": 4,
          "card_name": "Summon: Fenrir"
        },
        {
          "count": 1,
          "card_name": "Summon: Knights of Round"
        },
        {
          "count": 1,
          "card_name": "Swamp"
        },
        {
          "count": 2,
          "card_name": "Tear Asunder"
        },
        {
          "count": 3,
          "card_name": "Temporary Lockdown"
        },
        {
          "count": 3,
          "card_name": "Underground Mortuary"
        },
        {
          "count": 1,
          "card_name": "Virtue of Persistence"
        },
        {
          "count": 3,
          "card_name": "Wastewood Verge"
        },
        {
          "count": 3,
          "card_name": "Yuna, Hope of Spira"
        },
        {
          "count": 3,
          "card_name": "Zur, Eternal Schemer"
        }
      ],
      "sideboard": [
        {
          "count": 2,
          "card_name": "Beza, the Bounding Spring"
        },
        {
          "count": 2,
          "card_name": "Day of Judgment"
        },
        {
          "count": 4,
          "card_name": "Duress"
        },
        {
          "count": 2,
          "card_name": "Ghost Vacuum"
        },
        {
          "count": 2,
          "card_name": "Maelstrom Pulse"
        },
        {
          "count": 2,
          "card_name": "Nissa, Ascended Animist"
        },
        {
          "count": 1,
          "card_name": "Tear Asunder"
        }
      ]
    },
    {
      "player": "manukoka",
      "result": "31th Place",
      "rank": 31,
      "mainboard": [
        {
          "count": 2,
          "card_name": "Arabella, Abandoned Doll"
        },
        {
          "count": 4,
          "card_name": "Battlefield Forge"
        },
        {
          "count": 4,
          "card_name": "Case of the Gateway Express"
        },
        {
          "count": 2,
          "card_name": "Dragoon's Lance"
        },
        {
          "count": 1,
          "card_name": "Elegant Parlor"
        },
        {
          "count": 4,
          "card_name": "Gleeful Demolition"
        },
        {
          "count": 4,
          "card_name": "Imodane's Recruiter"
        },
        {
          "count": 4,
          "card_name": "Inspiring Vantage"
        },
        {
          "count": 4,
          "card_name": "Knight-Errant of Eos"
        },
        {
          "count": 1,
          "card_name": "Mirrex"
        },
        {
          "count": 1,
          "card_name": "Mountain"
        },
        {
          "count": 4,
          "card_name": "Nesting Bot"
        },
        {
          "count": 4,
          "card_name": "Novice Inspector"
        },
        {
          "count": 2,
          "card_name": "Painter's Studio // Defaced Gallery"
        },
        {
          "count": 5,
          "card_name": "Plains"
        },
        {
          "count": 4,
          "card_name": "Resolute Reinforcements"
        },
        {
          "count": 1,
          "card_name": "Sanguine Evangelist"
        },
        {
          "count": 1,
          "card_name": "Starting Town"
        },
        {
          "count": 4,
          "card_name": "Sunbillow Verge"
        },
        {
          "count": 4,
          "card_name": "Warden of the Inner Sky"
        }
      ],
      "sideboard": [
        {
          "count": 4,
          "card_name": "Aven Interrupter"
        },
        {
          "count": 2,
          "card_name": "Destroy Evil"
        },
        {
          "count": 3,
          "card_name": "Rest in Peace"
        },
        {
          "count": 2,
          "card_name": "Sheltered by Ghosts"
        },
        {
          "count": 4,
          "card_name": "Torch the Tower"
        }
      ]
    },
    {
      "player": "Mldyss",
      "result": "32th Place",
      "rank": 32,
      "mainboard": [
        {
          "count": 3,
          "card_name": "Adarkar Wastes"
        },
        {
          "count": 2,
          "card_name": "Beza, the Bounding Spring"
        },
        {
          "count": 2,
          "card_name": "Change the Equation"
        },
        {
          "count": 2,
          "card_name": "Demolition Field"
        },
        {
          "count": 1,
          "card_name": "Destroy Evil"
        },
        {
          "count": 2,
          "card_name": "Elspeth, Storm Slayer"
        },
        {
          "count": 1,
          "card_name": "Essence Scatter"
        },
        {
          "count": 4,
          "card_name": "Floodfarm Verge"
        },
        {
          "count": 3,
          "card_name": "Fountainport"
        },
        {
          "count": 4,
          "card_name": "Get Lost"
        },
        {
          "count": 3,
          "card_name": "Island"
        },
        {
          "count": 3,
          "card_name": "Marang River Regent"
        },
        {
          "count": 4,
          "card_name": "Meticulous Archive"
        },
        {
          "count": 4,
          "card_name": "No More Lies"
        },
        {
          "count": 4,
          "card_name": "Plains"
        },
        {
          "count": 2,
          "card_name": "Restless Anchorage"
        },
        {
          "count": 1,
          "card_name": "Ride's End"
        },
        {
          "count": 2,
          "card_name": "Seachrome Coast"
        },
        {
          "count": 1,
          "card_name": "Split Up"
        },
        {
          "count": 3,
          "card_name": "Stock Up"
        },
        {
          "count": 3,
          "card_name": "Temporary Lockdown"
        },
        {
          "count": 3,
          "card_name": "Three Steps Ahead"
        },
        {
          "count": 1,
          "card_name": "Tishana's Tidebinder"
        },
        {
          "count": 2,
          "card_name": "Ultima"
        }
      ],
      "sideboard": [
        {
          "count": 1,
          "card_name": "Cathar Commando"
        },
        {
          "count": 1,
          "card_name": "Destroy Evil"
        },
        {
          "count": 1,
          "card_name": "Faerie Mastermind"
        },
        {
          "count": 2,
          "card_name": "Ghost Vacuum"
        },
        {
          "count": 2,
          "card_name": "Jace, the Perfected Mind"
        },
        {
          "count": 1,
          "card_name": "Overlord of the Mistmoors"
        },
        {
          "count": 2,
          "card_name": "Stoic Sphinx"
        },
        {
          "count": 2,
          "card_name": "Tishana's Tidebinder"
        },
        {
          "count": 2,
          "card_name": "Voice of Victory"
        }
      ]
    }
  ]
}